skittle/app.py
skittle/drive.py
skittle_sheets-0.0.5.dist-info/LICENSE
skittle_sheets-0.0.5.dist-info/METADATA
skittle_sheets-0.0.5.dist-info/WHEEL
skittle_sheets-0.0.5.dist-info/entry_points.txt
skittle_sheets-0.0.5.dist-info/top_level.txt
skittle_sheets-0.0.5.dist-info/RECORD
