Metadata-Version: 2.1
Name: skittle-sheets
Version: 0.0.5
Summary: Lightweight design of plate-based experiments
Author: David Feldman
Project-URL: Homepage, https://github.com/feldman4/skittle-sheets
Project-URL: Bug Tracker, https://github.com/feldman4/skittle-sheets/issues
Keywords: lab,biology,plate,experimental design
Classifier: Programming Language :: Python :: 3
Classifier: License :: OSI Approved :: MIT License
Classifier: Operating System :: OS Independent
Requires-Python: >=3.9
License-File: LICENSE
Requires-Dist: fire
Requires-Dist: google-api-python-client
Requires-Dist: google-auth-httplib2
Requires-Dist: google-auth-oauthlib
Requires-Dist: pandas
Requires-Dist: pygsheets
Requires-Dist: pyyaml
